red_helper/__init__.py
red_helper/_base.py
red_helper/_exc.py
red_helper/cache.py
red_helper/counter.py
red_helper/objects.py
red_helper/types.py
red_helper-0.1.1.dist-info/LICENSE
red_helper-0.1.1.dist-info/METADATA
red_helper-0.1.1.dist-info/WHEEL
red_helper-0.1.1.dist-info/top_level.txt
red_helper-0.1.1.dist-info/RECORD
