Metadata-Version: 2.1
Name: red-helper
Version: 0.1.1
Summary: 基于异步IO的Redis缓存操作工具
Home-page: https://github.com/irealing/red-helper
Author: Memory_Leak
License: MIT
Platform: any
Requires-Python: >=3.8
